{
  "data": {
    "type": "galleries",
    "id": "neugeborene",
    "attributes": {
      "name": "Neugeborene",
      "title": "der beste Zeitpunkt für Eure Neugeborenenbilder",
      "link": "neugeborene",
      "description": "Ist dein Neugeborenes auf der Welt und noch nicht älter als 14 Tage, dann können wir wunderschöne und einmalige Fotos von deinem Baby entstehen lassen. Ein Neugeborenen-Shooting, um den Zauber dieses neuen Lebens festzuhalten!",
      "url": "img/gallery/neugeborene",
      "images": [
        "neugeborene_27.jpg", "neugeborene_26.jpg", "neugeborene_25.jpg", "neugeborene_24.jpg",
        "neugeborene_23.jpg", "neugeborene_22.jpg", "neugeborene_21.jpg", "neugeborene_20.jpg",
        "neugeborene_19.jpg", "neugeborene_18.jpg", "neugeborene_17.jpg", "neugeborene_16.jpg",
        "neugeborene_15.jpg", "neugeborene_14.jpg", "neugeborene_13.jpg", "neugeborene_12.jpg",
        "neugeborene_11.jpg", "neugeborene_10.jpg", "neugeborene_9.jpg", "neugeborene_8.jpg",
        "neugeborene_2.jpg", "neugeborene_1.jpg"
      ]
    }
  }
}
